ampel/py.typed
ampel/ztf/archive/ArchiveDB.py
ampel/ztf/archive/ArchiveDBClient.py
ampel/ztf/archive/ZUDSArchiveDB.py
ampel/ztf/archive/server/app.py
ampel/ztf/archive/server/models.py
ampel/ztf/archive/server/settings.py
ampel/ztf/t0/ArchiveUpdater.py
ampel/ztf/t0/ZUDSArchiveUpdater.py
ampel_ztf_archive-0.7.1.dist-info/entry_points.txt
ampel_ztf_archive-0.7.1.dist-info/LICENSE
ampel_ztf_archive-0.7.1.dist-info/WHEEL
ampel_ztf_archive-0.7.1.dist-info/METADATA
ampel_ztf_archive-0.7.1.dist-info/RECORD
